QDetect/__init__.py
QDetect/qdetect.py
QDetect/dfiles/nonTerminals.txt
QDetect/dfiles/quran-index.xml
QDetect/dfiles/quran-simple.txt
QDetect-0.7.2.dist-info/METADATA
QDetect-0.7.2.dist-info/WHEEL
QDetect-0.7.2.dist-info/top_level.txt
QDetect-0.7.2.dist-info/RECORD
